setup.py
ezhuthi/DocView.py
ezhuthi/ExampleHelper.py
ezhuthi/OSKeyboardWidget.py
ezhuthi/SplashActivity.py
ezhuthi/__init__.py
ezhuthi/__main__.py
ezhuthi/console.py
ezhuthi/demo.py
ezhuthi/ezhili.py
ezhuthi/ezhilpopuptools.py
ezhuthi/ezhuthi.py
ezhuthi/iyakki.py
ezhuthi/resources.py
ezhuthi/setup.py
ezhuthi/syntaxhighlighing.py
ezhuthi/testdriver.py
ezhuthi/undobuffer.py
ezhuthi.egg-info/PKG-INFO
ezhuthi.egg-info/SOURCES.txt
ezhuthi.egg-info/dependency_links.txt
ezhuthi.egg-info/entry_points.txt
ezhuthi.egg-info/requires.txt
ezhuthi.egg-info/top_level.txt
ezhuthi/res/LICENSE_notes.txt
ezhuthi/res/editor.glade
ezhuthi/res/editor.glade~
ezhuthi/res/fontchooser.glade
ezhuthi/res/helper.glade
ezhuthi/res/helper.glade~
ezhuthi/res/index.html
ezhuthi/res/img/Tamil-Ezhil-Introduction.pdf
ezhuthi/res/img/ezhil-logo.png
ezhuthi/res/img/ezhil-splash-5.png
ezhuthi/res/img/ezhil_download.png
ezhuthi/res/img/ezhil_download.xcf
ezhuthi/res/img/ezhil_square_2015_128px.png
ezhuthi/res/img/small-ezhil-splash-5.png