Metadata-Version: 1.1
Name: ezhuthi
Version: 0.99
Summary: Ezhuthi - a GTK based GUI for Ezhil (Tamil programming language) Python 2 and Python 3
Home-page: https://github.com/Ezhil-Language-Foundation/Ezhil-Lang
Author: Muthiah Annamalai
Author-email: ezhillang@gmail.com
License: GPLv3
Download-URL: https://github.com/Ezhil-Language-Foundation/Ezhil-Lang/archive/latest.zip
Platform: PC
Platform: Linux
Platform: Mac
Classifier: Natural Language :: Tamil
Classifier: Programming Language :: Python :: 2.6
Classifier: Programming Language :: Python :: 2.7
Classifier: Programming Language :: Python :: 3
Classifier: Programming Language :: Python :: 3.2
Classifier: Programming Language :: Python :: 3.3
Classifier: Programming Language :: Python :: 3.4
